CODING-STYLE.md
CONTRIBUTING.md
LICENSE
MANIFEST.in
NOTICE
README
README.md
mockapi.conf
requirements-test.txt
requirements.txt
setup.cfg
setup.py
docs/options.md
lacore/__init__.py
lacore/api.py
lacore/async.py
lacore/auth.py
lacore/crypt.py
lacore/date.py
lacore/decorators.py
lacore/enc.py
lacore/exceptions.py
lacore/log.py
lacore.egg-info/PKG-INFO
lacore.egg-info/SOURCES.txt
lacore.egg-info/dependency_links.txt
lacore.egg-info/requires.txt
lacore.egg-info/top_level.txt
lacore/adf/__init__.py
lacore/adf/elements.py
lacore/adf/persist.py
lacore/adf/serialize.py
lacore/adf/util.py
lacore/archive/__init__.py
lacore/archive/folders.py
lacore/archive/urls.py
lacore/archive/zip.py
lacore/cipher/__init__.py
lacore/cipher/aes.py
lacore/cipher/base.py
lacore/cipher/xor.py
lacore/dumper/__init__.py
lacore/dumper/file.py
lacore/dumper/s3.py
lacore/dumper/urls.py
lacore/source/__init__.py
lacore/source/chunked.py
lacore/source/stream.py
lacore/storage/__init__.py
lacore/storage/s3/__init__.py
lacore/t/__init__.py
lacore/t/test_adf.py
lacore/t/test_aes.py
lacore/t/test_api.py
lacore/t/test_api_async.py
lacore/t/test_api_http.py
lacore/t/test_archive.py
lacore/t/test_async.py
lacore/t/test_cipher.py
lacore/t/test_crypt.py
lacore/t/test_date.py
lacore/t/test_dumper.py
lacore/t/test_dumper_s3.py
lacore/t/test_exceptions.py
lacore/t/test_mpconnection.py
lacore/t/test_s3.py
lacore/t/test_source_chunked.py
lacore/t/test_source_stream.py
lacore/t/data/2013-10-22-foobar.zip.crypt
lacore/t/data/longaccess-74-5N93.html
lacore/t/data/archives/invalid.adf
lacore/t/data/archives/minimal.adf
lacore/t/data/archives/sample.adf
lacore/t/data/certs/2013-10-13-foobar.adf
scripts/nose.sh