Metadata-Version: 1.1
Name: lacore
Version: 0.1.3.1
Summary: The Long Access Python SDK - Core
Home-page: http://github.com/longaccess/longaccess-core/
Author: Konstantinos Koukopoulos
Author-email: kk@longaccess.com
License: Apache
Platform: UNKNOWN
Classifier: Development Status :: 4 - Beta
Classifier: Intended Audience :: Developers
Classifier: Intended Audience :: System Administrators
Classifier: Intended Audience :: Information Technology
Classifier: Natural Language :: English
Classifier: License :: OSI Approved :: Apache Software License
Classifier: Operating System :: OS Independent
Classifier: Programming Language :: Python
Classifier: Programming Language :: Python :: 2
Classifier: Programming Language :: Python :: 2.6
Classifier: Programming Language :: Python :: 2.7
Classifier: Topic :: System :: Archiving
Classifier: Topic :: Utilities
